{
    "version": "https://jsonfeed.org/version/1",
    "title": "新浪新闻",
    "home_page_url": "https://ruanyf.github.io/sina-news/",
    "feed_url": "https://ruanyf.github.io/sina-news/rss.json",
    "description": "新浪全球实时财经新闻直播",
    "items": [
        {
            "id": 1930692,
            "content_html": "",
            "url": "https://finance.sina.cn/7x24/2020-12-15/detail-iiznezxs6947023.d.html",
            "title": "【私募明年布局思路曝光：看多也做多】华润信托阳光私募股票多头指数（CREFI指数）月报显示，11月末，该指数成分基金的平均股票仓位为78.52%，较10月末上升1.44个百分点，已连续两个月提升。多位业内人士表示，短期部分标的存在估值回归的风险，但消费、科技与医药为中长期看好的三大黄金赛道，随着优质标的估值回归合理区间，明年投资机会值得关注。（上证报）",
            "date_modified": "2020-12-14T22:27:11.000Z"
        },
        {
            "id": 1930691,
            "content_html": "",
            "url": "https://finance.sina.cn/7x24/2020-12-15/detail-iiznezxs6946833.d.html",
            "title": "周一（12月14日）纽约尾盘，CME比特币期货BTC主力合约报19260美元，较上周五涨6.88%，盘中交投于19080-19430美元区间，上周累跌逾5.1%。",
            "date_modified": "2020-12-14T22:21:14.000Z"
        },
        {
            "id": 1930690,
            "content_html": "",
            "url": "https://finance.sina.cn/7x24/2020-12-15/detail-iiznctke6529988.d.html",
            "title": "离岸人民币（CNH）兑美元北京时间05:59报6.5290元，较上周五纽约尾盘涨107点，盘中整体交投于6.5400-6.5168元区间。",
            "date_modified": "2020-12-14T22:21:08.000Z"
        },
        {
            "id": 1930689,
            "content_html": "",
            "url": "https://finance.sina.cn/7x24/2020-12-15/detail-iiznctke6529958.d.html",
            "title": "【前10月险资股票投资收益率8.74%】数据显示，截至今年10月末，保险资金股票投资余额1.75万亿元，占保险资金运用余额的8.41%。今年前10个月，保险资金股票投资收益1468.40亿元，股票投资收益率达8.74%。（上证报）",
            "date_modified": "2020-12-14T22:20:35.000Z"
        },
        {
            "id": 1930688,
            "content_html": "",
            "url": "https://finance.sina.cn/7x24/2020-12-15/detail-iiznezxs6946670.d.html",
            "title": "  【美国选举人团投票，六大争议州均支持拜登当选】据媒体报道，周一举行的美国选举人团投票，包括宾夕法尼亚、佐治亚、密歇根、威斯康星、内华达和亚利桑那六个争议最大的州均投票支持拜登当选下一任美国总统。",
            "date_modified": "2020-12-14T22:17:42.000Z"
        },
        {
            "id": 1930687,
            "content_html": "",
            "url": "https://finance.sina.cn/7x24/2020-12-15/detail-iiznctke6529731.d.html",
            "title": "  据证券日报： 从今年5月份至11月份，LPR1年期及5年期品种均分别维持在3.85%、4.65%水平，连续7个月“原地踏步”。苏宁金融研究院宏观经济研究中心副主任陶金表示，年内LPR调降空间已经很小，预计12月份LPR大概率仍将保持不变。",
            "date_modified": "2020-12-14T22:15:21.000Z"
        },
        {
            "id": 1930686,
            "content_html": "",
            "url": "https://finance.sina.cn/7x24/2020-12-15/detail-iiznezxs6946516.d.html",
            "title": "泡泡玛特：悉数行使2035.72万股超额配售股份，本公司将按每股38.50港元发行及配发超额配售股份。超额配售股份将用于向GWF Holding Limited归还用于补足国际发售中超额分配股份的2035.72万股股份。",
            "date_modified": "2020-12-14T22:14:08.000Z"
        },
        {
            "id": 1930685,
            "content_html": "",
            "url": "https://finance.sina.cn/7x24/2020-12-15/detail-iiznctke6529692.d.html",
            "title": "富士电机株式会社到2023财年将在电动汽车芯片领域投资1200亿日元。",
            "date_modified": "2020-12-14T22:13:59.000Z"
        },
        {
            "id": 1930684,
            "content_html": "",
            "url": "https://finance.sina.cn/7x24/2020-12-15/detail-iiznezxs6946229.d.html",
            "title": "【寻求突破：美两党议员将9080亿美元救助一分为二】一个提案规模7480亿美元，含资助小企业3000亿美元；每周300美元失业救济补助，以及疫苗分发资金。另一提案包含企业免责保护以及援助州和地方政府1600亿美元。",
            "date_modified": "2020-12-14T22:07:56.000Z"
        },
        {
            "id": 1930683,
            "content_html": "",
            "url": "https://finance.sina.cn/7x24/2020-12-15/detail-iiznctke6529275.d.html",
            "title": "  据日本放送协会NHK调查：日本内阁支持率下降14个百分点至42％。",
            "date_modified": "2020-12-14T22:07:04.000Z"
        },
        {
            "id": 1930682,
            "content_html": "",
            "url": "https://finance.sina.cn/7x24/2020-12-15/detail-iiznezxs6946145.d.html",
            "title": "  据CME“美联储观察”：美联储12月维持利率在0%-0.25%区间的概率为100%，加息25个基点至0.25%-0.50%区间的概率为0%；明年1月维持利率在0%-0.25%区间的概率为100%，加息25个基点的概率为0%。",
            "date_modified": "2020-12-14T22:06:54.000Z"
        },
        {
            "id": 1930681,
            "content_html": "",
            "url": "https://finance.sina.cn/7x24/2020-12-15/detail-iiznezxs6945899.d.html",
            "title": "据媒体报道：日本央行考虑将公司债购买计划延长6个月时间。",
            "date_modified": "2020-12-14T22:01:48.000Z"
        },
        {
            "id": 1930680,
            "content_html": "",
            "url": "https://finance.sina.cn/7x24/2020-12-15/detail-iiznezxs6945819.d.html",
            "title": "  澳大利亚审慎监管局：压力测试表明，澳大利亚的银行体系能够承受非常严重的经济衰退，并继续提供信贷。",
            "date_modified": "2020-12-14T21:59:37.000Z"
        },
        {
            "id": 1930679,
            "content_html": "",
            "url": "https://finance.sina.cn/7x24/2020-12-15/detail-iiznezxs6945656.d.html",
            "title": "公募基金人士普遍表示，当前经济景气度向上的趋势延续，A股岁末年初行情可期，春季行情有望持续到明年3月中旬，消费、科技、周期等板块或轮动演绎。（中证报）",
            "date_modified": "2020-12-14T21:56:45.000Z"
        },
        {
            "id": 1930678,
            "content_html": "",
            "url": "https://finance.sina.cn/7x24/2020-12-15/detail-iiznctke6528488.d.html",
            "title": "  美国参议员Angus King：并未在对各州援助以及责任条款问题上达成共识。",
            "date_modified": "2020-12-14T21:50:14.000Z"
        },
        {
            "id": 1930677,
            "content_html": "",
            "url": "https://finance.sina.cn/7x24/2020-12-15/detail-iiznezxs6945004.d.html",
            "title": "  【美国跨党派议员小组公布抗疫援助计划提案】美国跨党派议员小组周一公布了他们针对疫情提出的9080亿美元刺激法案的细节。该法案分为两部分，第一个部分是规模为7480亿美元的救助计划，其中包括向小型企业提供的近3000亿美元救助资金、疫苗分发援助以及每周额外300美元的失业津贴。法案的第二部分只有两个内容，分别是民主党寻求的1600亿美元州政府援助，以及共和党认为应纳入援助计划的责任条款。但这些条款能否落实仍取决于国会两党领导人就立法条款进行的谈判。",
            "date_modified": "2020-12-14T21:37:20.000Z"
        },
        {
            "id": 1930676,
            "content_html": "",
            "url": "https://finance.sina.cn/7x24/2020-12-15/detail-iiznezxs6944683.d.html",
            "title": "  美国国会参议院多数党党鞭Cornyn：参议院多数党（共和党）领袖麦康奈尔与众议院议长佩洛西一直在进行谈话。",
            "date_modified": "2020-12-14T21:34:17.000Z"
        },
        {
            "id": 1930675,
            "content_html": "",
            "url": "https://finance.sina.cn/7x24/2020-12-15/detail-iiznctke6527639.d.html",
            "title": "Kezar生命科学（KZR）美股盘后涨超14%，该股被纳入纳斯达克生物科技指数。",
            "date_modified": "2020-12-14T21:29:51.000Z"
        },
        {
            "id": 1930674,
            "content_html": "",
            "url": "https://finance.sina.cn/7x24/2020-12-15/detail-iiznezxs6944404.d.html",
            "title": "世卫组织：没有证据显示英国出现的变异病毒表现有所不同。（央视）",
            "date_modified": "2020-12-14T21:24:08.000Z"
        },
        {
            "id": 1930673,
            "content_html": "",
            "url": "https://finance.sina.cn/7x24/2020-12-15/detail-iiznctke6527453.d.html",
            "title": "  【苹果正式发布iOS 14.3 Apple ProRAW来了】今日凌晨，苹果正式发布 iOS 14.3 、iPadOS 14.3 正式版以及watchOS 7.2 正式版更新。iOS 14.3 包括了对 Apple Fitness+ 和 AirPods Max 的支持。本更新还新增了在 iPhone 12 Pro 上拍摄 Apple ProRAW 照片的功能.",
            "date_modified": "2020-12-14T21:22:04.000Z"
        },
        {
            "id": 1930672,
            "content_html": "",
            "url": "https://finance.sina.cn/7x24/2020-12-15/detail-iiznctke6527444.d.html",
            "title": "  美国加州州长：今天收到3.35万剂新冠疫苗。",
            "date_modified": "2020-12-14T21:21:36.000Z"
        },
        {
            "id": 1930671,
            "content_html": "",
            "url": "https://finance.sina.cn/7x24/2020-12-15/detail-iiznezxs6943848.d.html",
            "title": "  市场消息：美国两党刺激法案小组就责任问题达成妥协。",
            "date_modified": "2020-12-14T21:05:08.000Z"
        },
        {
            "id": 1930670,
            "content_html": "",
            "url": "https://finance.sina.cn/7x24/2020-12-15/detail-iiznezxs6943798.d.html",
            "title": "  巴西报告新增25193例新冠肺炎确诊病例，新增433例死亡病例。",
            "date_modified": "2020-12-14T21:03:45.000Z"
        },
        {
            "id": 1930669,
            "content_html": "",
            "url": "https://finance.sina.cn/7x24/2020-12-15/detail-iiznezxs6943751.d.html",
            "title": "热门中概股涨跌各异，小鹏汽车涨超6%，拼多多、阿里巴巴、京东跌超3%。",
            "date_modified": "2020-12-14T21:02:42.000Z"
        },
        {
            "id": 1930668,
            "content_html": "",
            "url": "https://finance.sina.cn/7x24/2020-12-15/detail-iiznezxs6943744.d.html",
            "title": "美股科技股涨跌各异，特斯拉涨4.8%，芯片股普遍上涨，AMD涨超3%，英特尔涨超2%。",
            "date_modified": "2020-12-14T21:02:29.000Z"
        },
        {
            "id": 1930667,
            "content_html": "",
            "url": "https://finance.sina.cn/7x24/2020-12-15/detail-iiznezxs6943735.d.html",
            "title": "  市场消息；拜登表示，当务之急是接种疫苗以及提出经济刺激法案。",
            "date_modified": "2020-12-14T21:02:16.000Z"
        },
        {
            "id": 1930666,
            "content_html": "",
            "url": "https://finance.sina.cn/7x24/2020-12-15/detail-iiznezxs6943676.d.html",
            "title": "  美股收盘，三大指数涨跌互现，道指初步收跌约190点，银行股走高，能源股下挫。",
            "date_modified": "2020-12-14T21:00:26.000Z"
        },
        {
            "id": 1930665,
            "content_html": "",
            "url": "https://finance.sina.cn/7x24/2020-12-15/detail-iiznezxs6943643.d.html",
            "title": "美国国立过敏与传染病研究所（NIAID）所长Fauci：Moderna和辉瑞制药的疫苗接种存在相似性，那将印证加速防疫的看法。接种新冠疫苗将给抗击其他疾病带去取得成功的希望。",
            "date_modified": "2020-12-14T20:59:50.000Z"
        },
        {
            "id": 1930664,
            "content_html": "",
            "url": "https://finance.sina.cn/7x24/2020-12-15/detail-iiznezxs6943210.d.html",
            "title": "道指日内跌幅扩大至0.5%，标普500指数跌0.41%。",
            "date_modified": "2020-12-14T20:46:25.000Z"
        },
        {
            "id": 1930663,
            "content_html": "",
            "url": "https://finance.sina.cn/7x24/2020-12-15/detail-iiznezxs6943199.d.html",
            "title": "Uber因不配合袭击调查而被美国加州罚款5900万美元，如果30天之内没有支付罚金，将被暂停在加州运营的许可。",
            "date_modified": "2020-12-14T20:46:17.000Z"
        },
        {
            "id": 1930662,
            "content_html": "",
            "url": "https://finance.sina.cn/7x24/2020-12-15/detail-iiznezxs6943020.d.html",
            "title": "【美国新冠肺炎死亡病例超过30万】约翰斯·霍普金斯大学数据显示，美国累计确诊16351259例新冠肺炎病例，死亡病例达到300267例。12月14日当天，美国接种辉瑞制药新冠疫苗的工作已经铺开。",
            "date_modified": "2020-12-14T20:41:58.000Z"
        },
        {
            "id": 1930661,
            "content_html": "",
            "url": "https://finance.sina.cn/7x24/2020-12-15/detail-iiznctke6525901.d.html",
            "title": "【深圳新房审查趋严，购房者渐趋谨慎】刚刚过去的周末，位于深圳沙井的一处新盘开盘，现场“弃购”者超过300人。类似“日光”盘的背后，选房顺序靠前却“弃购”的情况在近期已经不止一次出现，就在市场热度极高的南山区，市场也传出有新房项目出现购房者现场“弃购”的现象。美联物业全国研究中心认为，近期深圳新房入市脚步不松懈，仅在上周就有8个项目入市销售，但项目去化率较前期有所回稳，售罄率降低。估计下一步，政府会以加大资金监管力度为主，以减少代持现象的出现，楼市调控政策收紧的信号灯又再亮起。（证券时报）",
            "date_modified": "2020-12-14T20:39:18.000Z"
        },
        {
            "id": 1930660,
            "content_html": "",
            "url": "https://finance.sina.cn/7x24/2020-12-15/detail-iiznezxs6942694.d.html",
            "title": "  【美国国会接近就2021财年全面支出法案达成一致】Politico报道称，美国国会谈判代表接近敲定一项规模为1.4万亿美元的2021财年全面支出法案，以避免政府在周五午夜陷入“关门”的窘境，这将为立法议程上的一项主要优先事项划上了句号，并增加了将疫情援助法案纳入年底一揽子立法计划的紧迫性。三名消息人士证实，议员们最早可能于周一宣布一项妥协方案，立法文本预计将于周二公布。据一位共和党助手透露，目前只有“几个小项目”的支出数目仍未敲定。",
            "date_modified": "2020-12-14T20:36:35.000Z"
        },
        {
            "id": 1930659,
            "content_html": "",
            "url": "https://finance.sina.cn/7x24/2020-12-15/detail-iiznezxs6942682.d.html",
            "title": "  道指跌超100点，标普500指数跌0.22%，纳指涨幅收窄至0.7%。",
            "date_modified": "2020-12-14T20:36:27.000Z"
        },
        {
            "id": 1930658,
            "content_html": "",
            "url": "https://finance.sina.cn/7x24/2020-12-15/detail-iiznctke6525409.d.html",
            "title": "【证券时报头版评论：退市制度全面升级，A股加速“祛腐排毒”】12月14日，沪深证券交易所发布改革后的退市制度征求意见稿。首先，在A股市场全面推进注册制改革的预期下，健全常态化退市机制能为IPO常态化保驾护航。其次，资本市场具有其特殊的功能和作用，既应该拥有强大的包容度，也要通过信息披露对企业运营形成强烈的约束和筛选效应。“流水不腐、户枢不蠹”，畅通多元化退出渠道，促进市场优胜劣汰、新陈代谢，一个规范、透明、开放、有活力、有韧性的资本市场可期。",
            "date_modified": "2020-12-14T20:32:34.000Z"
        },
        {
            "id": 1930657,
            "content_html": "",
            "url": "https://finance.sina.cn/7x24/2020-12-15/detail-iiznctke6525162.d.html",
            "title": "  【美国针对土耳其购买S-400实施制裁 土外交部：谴责并拒绝这一决定】针对美国宣布就土耳其购买俄制S-400防空导弹系统对土实施制裁，土耳其外交部连夜发表声明，谴责并拒绝美对土实施单方面制裁的决定。声明指出，“土耳其购买俄制S-400反导系统的原因众所周知，此前美国总统特朗普本人也曾多次在不同场合承认土方此举是合理的。”声明还强调，美国拒绝土方通过对话和外交途径解决问题的提议，并对土方采取单方面制裁，此举完全没有道理。（央视）",
            "date_modified": "2020-12-14T20:26:27.000Z"
        },
        {
            "id": 1930656,
            "content_html": "",
            "url": "https://finance.sina.cn/7x24/2020-12-15/detail-iiznezxs6942046.d.html",
            "title": "【特斯拉市值超过九大汽车制造商之和，但全球销量仅占不到1%】特斯拉目前上涨近5%，市值报6054亿美元，据CNBC，该股市值今年增加了超过5000亿美元，截至目前市值已经超过了包括大众、丰田、日产、现代、通用汽车、福特汽车、本田汽车、菲亚特克莱斯勒以及标致等九大汽车制造商的市值之和。与此同时，特斯拉预计今年将在全球销售至少50万辆电动汽车，占全球汽车总销量的不到1%。",
            "date_modified": "2020-12-14T20:26:10.000Z"
        },
        {
            "id": 1930655,
            "content_html": "",
            "url": "https://finance.sina.cn/7x24/2020-12-15/detail-iiznctke6524752.d.html",
            "title": "  美国参议院多数党（共和党）领袖麦康奈尔：现在是时候完成有关援助法案的谈判了。",
            "date_modified": "2020-12-14T20:16:31.000Z"
        },
        {
            "id": 1930654,
            "content_html": "",
            "url": "https://finance.sina.cn/7x24/2020-12-15/detail-iiznctke6524671.d.html",
            "title": "  美国参议院多数党（共和党）领袖麦康奈尔：国会需要在疫情援助问题上采取行动。",
            "date_modified": "2020-12-14T20:13:32.000Z"
        },
        {
            "id": 1930653,
            "content_html": "",
            "url": "https://finance.sina.cn/7x24/2020-12-15/detail-iiznctke6524665.d.html",
            "title": "拜登计划12月14日美东时间07:30（北京时间12月15日08:30）发表全美讲话。",
            "date_modified": "2020-12-14T20:13:22.000Z"
        },
        {
            "id": 1930652,
            "content_html": "",
            "url": "https://finance.sina.cn/7x24/2020-12-15/detail-iiznctke6524445.d.html",
            "title": "  美国北达科他州10月原油产量为122.2871万桶/日。",
            "date_modified": "2020-12-14T20:09:34.000Z"
        },
        {
            "id": 1930651,
            "content_html": "",
            "url": "https://finance.sina.cn/7x24/2020-12-15/detail-iiznctke6524338.d.html",
            "title": "  【三大巨头同日被市场监管总局罚款，互联网行业步入反垄断强监管时代】国家市场监管总局对于阿里巴巴、阅文以及丰巢网络未依法申报违法实施集中案的行政处罚影响正在发酵。市场人士普遍判断，从目前的行业反馈来看，处罚产生的威慑警示作用远大于罚款本身，平台经济和互联网行业不是反垄断法外之地，从长远来看，企业无论规模大小，交易以及经营过程中的反垄断合规势在必行，互联网行业将迎来反垄断强监管时代。（证券日报）",
            "date_modified": "2020-12-14T20:07:11.000Z"
        },
        {
            "id": 1930650,
            "content_html": "",
            "url": "https://finance.sina.cn/7x24/2020-12-15/detail-iiznctke6524324.d.html",
            "title": "谷歌CEO将员工重返办公室推迟到明年9月，但放弃了永久性居家办公的想法。",
            "date_modified": "2020-12-14T20:06:33.000Z"
        },
        {
            "id": 1930649,
            "content_html": "",
            "url": "https://finance.sina.cn/7x24/2020-12-15/detail-iiznezxs6940344.d.html",
            "title": "  据道琼斯：美国两党立法小组将宣布在（与疫情相关的）责任问题上达成妥协。",
            "date_modified": "2020-12-14T19:50:18.000Z"
        },
        {
            "id": 1930648,
            "content_html": "",
            "url": "https://finance.sina.cn/7x24/2020-12-15/detail-iiznctke6523186.d.html",
            "title": "  美国商务部：将在12月23日发布11月耐用品报告，此前计划为12月24日。",
            "date_modified": "2020-12-14T19:44:54.000Z"
        },
        {
            "id": 1930647,
            "content_html": "",
            "url": "https://finance.sina.cn/7x24/2020-12-15/detail-iiznezxs6939688.d.html",
            "title": "  波音：正与供应商一同检查波音787梦想客机的框架是否存在新缺陷。",
            "date_modified": "2020-12-14T19:37:30.000Z"
        },
        {
            "id": 1930646,
            "content_html": "",
            "url": "https://finance.sina.cn/7x24/2020-12-15/detail-iiznezxs6939668.d.html",
            "title": "WTI 1月原油期货收涨0.42美元，涨幅0.90%，报46.99美元/桶，上周累涨约0.7%。",
            "date_modified": "2020-12-14T19:37:12.000Z"
        },
        {
            "id": 1930645,
            "content_html": "",
            "title": "  【各地争相布局，加快培育新能源汽车产业】近一个多月来，已有河南、合肥、昆明、广州等地做出规划和部署，包括完善新能源汽车技术创新体系，加快建设基础设施，培育行业领军企业，瞄准千亿市场空间加快培育新能源汽车产业等。（经参）",
            "date_modified": "2020-12-14T19:34:50.000Z"
        },
        {
            "id": 1930644,
            "content_html": "",
            "url": "https://finance.sina.cn/7x24/2020-12-15/detail-iiznctke6522733.d.html",
            "title": "  市场消息：美国阿拉斯加州已收到第一批交付的新冠疫苗，预计将很快收到更多疫苗。",
            "date_modified": "2020-12-14T19:34:46.000Z"
        },
        {
            "id": 1930643,
            "content_html": "",
            "url": "https://finance.sina.cn/7x24/2020-12-15/detail-iiznctke6522338.d.html",
            "title": "英国新增20263例新冠肺炎病例，新增232例死亡病例。",
            "date_modified": "2020-12-14T19:25:28.000Z"
        },
        {
            "id": 1930642,
            "content_html": "",
            "url": "https://finance.sina.cn/7x24/2020-12-15/detail-iiznezxs6938670.d.html",
            "title": "  【荷兰首相宣布实施“硬封锁” 所有中小学校将改网上授课】荷兰政府宣布，12月15日至明年1月19日，包括百货商场、服装店等在内的“非必须品”商店将关闭，体育健身场所、理发店、博物馆、动物园等也不允许营业。从12月16日起，荷兰全国范围的所有中小学校将停止上课，一律改为网上教学。",
            "date_modified": "2020-12-14T19:14:06.000Z"
        },
        {
            "id": 1930641,
            "content_html": "",
            "url": "https://finance.sina.cn/7x24/2020-12-15/detail-iiznezxs6938412.d.html",
            "title": "据路透测算：美国新冠肺炎死亡病例累计超30万例。",
            "date_modified": "2020-12-14T19:08:55.000Z"
        },
        {
            "id": 1930640,
            "content_html": "",
            "url": "https://finance.sina.cn/7x24/2020-12-15/detail-iiznezxs6938289.d.html",
            "title": "  美国能源信息署（EIA）：预计1月份美国巴肯地区石油产量将减少约2.3万桶/日至119.7万桶/日。(12月份为减少1.3万桶/日)",
            "date_modified": "2020-12-14T19:06:14.000Z"
        },
        {
            "id": 1930639,
            "content_html": "",
            "url": "https://finance.sina.cn/7x24/2020-12-15/detail-iiznezxs6938198.d.html",
            "title": "  美国能源信息署（EIA）：预计1月份美国二叠纪盆地石油产量将减少约4.4万桶/日至419.6万桶/日。(12月份为减少3.5万桶/日)",
            "date_modified": "2020-12-14T19:04:59.000Z"
        },
        {
            "id": 1930638,
            "content_html": "",
            "url": "https://finance.sina.cn/7x24/2020-12-15/detail-iiznctke6521385.d.html",
            "title": "  美国能源信息署（EIA）：预计1月份美国页岩油总产量将减少约13.6万桶/日至743.9万桶/日。(12月份为减少12.5万桶/日)",
            "date_modified": "2020-12-14T19:04:03.000Z"
        },
        {
            "id": 1930637,
            "content_html": "",
            "url": "https://finance.sina.cn/7x24/2020-12-15/detail-iiznctke6520894.d.html",
            "title": "COMEX 2月黄金期货收跌0.6%，报1832.10美元/盎司。",
            "date_modified": "2020-12-14T18:54:12.000Z"
        },
        {
            "id": 1930636,
            "content_html": "",
            "url": "https://finance.sina.cn/7x24/2020-12-15/detail-iiznezxs6937494.d.html",
            "title": "美国联邦贸易委员会（FTC）将调查亚马逊、推特、以及Facebook的隐私保护实践。",
            "date_modified": "2020-12-14T18:50:22.000Z"
        },
        {
            "id": 1930635,
            "content_html": "",
            "url": "https://finance.sina.cn/7x24/2020-12-15/detail-iiznctke6520654.d.html",
            "title": "波音（BA）股价短线下挫大约3美元，日内整体上从上涨0.8%转变为下跌约0.8%，刷新日低至228.75美元。据道琼斯新闻报道，波音梦想客机（Dreamliner）被发现缺陷之后，该公司扩大调查范围。",
            "date_modified": "2020-12-14T18:49:04.000Z"
        },
        {
            "id": 1930634,
            "content_html": "",
            "url": "https://finance.sina.cn/7x24/2020-12-15/detail-iiznezxs6937065.d.html",
            "title": "美国纽约州州长Cuomo：纽约州新增9044例新冠肺炎病例，增幅1.2%（七天均值为1.3%）。",
            "date_modified": "2020-12-14T18:40:13.000Z"
        },
        {
            "id": 1930633,
            "content_html": "",
            "url": "https://finance.sina.cn/7x24/2020-12-15/detail-iiznezxs6936561.d.html",
            "title": "  上海黄金交易所黄金T+D 12月15日（周二）晚盘收盘下跌0.38%报379.9元/克；上海黄金交易所白银T+D 12月15日（周二）晚盘收盘下跌0.04%报4948.0元/千克。",
            "date_modified": "2020-12-14T18:30:20.000Z"
        },
        {
            "id": 1930632,
            "content_html": "",
            "url": "https://finance.sina.cn/7x24/2020-12-15/detail-iiznctke6519676.d.html",
            "title": "  美、布两油短线上扬0.2美元，分别报46.70美元/桶和50.08美元/桶。",
            "date_modified": "2020-12-14T18:27:45.000Z"
        },
        {
            "id": 1930631,
            "content_html": "",
            "url": "https://finance.sina.cn/7x24/2020-12-15/detail-iiznctke6519656.d.html",
            "title": "小鹏汽车刷新日高，目前上涨约5%；此前德意志银行首次覆盖该公司，并给予其买入评级，称该公司的软件优势将会受到更年轻消费者的青睐，到2025年该公司的软件销售额可能达到18亿元人民币，到40年代可能达到42亿元。",
            "date_modified": "2020-12-14T18:27:29.000Z"
        },
        {
            "id": 1930630,
            "content_html": "",
            "url": "https://finance.sina.cn/7x24/2020-12-15/detail-iiznezxs6936415.d.html",
            "title": "  苏丹总理：苏丹将很快获得840万剂的新冠疫苗。",
            "date_modified": "2020-12-14T18:27:08.000Z"
        },
        {
            "id": 1930629,
            "content_html": "",
            "url": "https://finance.sina.cn/7x24/2020-12-15/detail-iiznezxs6936347.d.html",
            "title": "英国首席医疗官Chris Whitty：没有证据表明新冠肺炎病毒变异之后的危险性提高。",
            "date_modified": "2020-12-14T18:25:53.000Z"
        },
        {
            "id": 1930628,
            "content_html": "",
            "url": "https://finance.sina.cn/7x24/2020-12-15/detail-iiznctke6519221.d.html",
            "title": "  欧盟药品监管机构表示，关于辉瑞的新冠疫苗（紧急使用授权）决定可能会在12月29日之前做出。",
            "date_modified": "2020-12-14T18:19:21.000Z"
        },
        {
            "id": 1930627,
            "content_html": "",
            "url": "https://finance.sina.cn/7x24/2020-12-15/detail-iiznezxs6935794.d.html",
            "title": "继道指之后，标普500指数转跌；纳指涨幅收窄至0.65%。",
            "date_modified": "2020-12-14T18:15:38.000Z"
        },
        {
            "id": 1930626,
            "content_html": "",
            "url": "https://finance.sina.cn/7x24/2020-12-15/detail-iiznctke6518344.d.html",
            "title": "  英国卫生大臣汉考克：不排除为应对疫情采取进一步的措施。",
            "date_modified": "2020-12-14T18:06:44.000Z"
        },
        {
            "id": 1930625,
            "content_html": "",
            "url": "https://finance.sina.cn/7x24/2020-12-15/detail-iiznctke6518198.d.html",
            "title": "  美、布两油期货转涨，此前跌幅一度扩大至1%。",
            "date_modified": "2020-12-14T18:04:37.000Z"
        },
        {
            "id": 1930624,
            "content_html": "",
            "url": "https://finance.sina.cn/7x24/2020-12-15/detail-iiznezxs6934871.d.html",
            "title": "  墨西哥外长：俄罗斯新冠疫苗“卫星-V”已经申请在墨西哥进行临床试验。",
            "date_modified": "2020-12-14T18:01:52.000Z"
        },
        {
            "id": 1930623,
            "content_html": "",
            "url": "https://finance.sina.cn/7x24/2020-12-15/detail-iiznezxs6934433.d.html",
            "title": "  【美联储本周或不出台更多刺激措施】机构经济学家指出，美联储本周可能会避免出台更多刺激措施，但会加大鸽派措辞，并强调有必要提供更多财政支持，因新冠疫情遏制措施对经济活动的影响越来越大。政策微调以限制收益率曲线趋陡是可能的，但可能会推迟到明年行动。",
            "date_modified": "2020-12-14T17:53:45.000Z"
        },
        {
            "id": 1930622,
            "content_html": "",
            "url": "https://finance.sina.cn/7x24/2020-12-15/detail-iiznezxs6934374.d.html",
            "title": "土耳其里拉兑美元维持0.42%的跌幅，暂报7.8892里拉，美国宣布制裁土耳其。",
            "date_modified": "2020-12-14T17:52:29.000Z"
        },
        {
            "id": 1930621,
            "content_html": "",
            "url": "https://finance.sina.cn/7x24/2020-12-15/detail-iiznctke6517386.d.html",
            "title": "东芝和富士电机株式会社将向电动汽车动力芯片投资20亿美元。",
            "date_modified": "2020-12-14T17:50:00.000Z"
        },
        {
            "id": 1930620,
            "content_html": "",
            "url": "https://finance.sina.cn/7x24/2020-12-15/detail-iiznezxs6934209.d.html",
            "title": "道指转跌，此前一度涨0.93%；迪士尼领跌，跌2.9%，此前BMO下调迪士尼评级；雪佛龙、美国运通跌超2%。麦当劳领涨道指成分股，涨2.4%，此前瑞银上调其评级。VIX波动率日内涨幅达2.5%，报23.92。",
            "date_modified": "2020-12-14T17:49:49.000Z"
        },
        {
            "id": 1930619,
            "content_html": "",
            "url": "https://finance.sina.cn/7x24/2020-12-15/detail-iiznctke6517140.d.html",
            "title": "  美元兑俄罗斯卢布USD/RUB突破74，日内涨1.54%。",
            "date_modified": "2020-12-14T17:44:44.000Z"
        },
        {
            "id": 1930618,
            "content_html": "",
            "url": "https://finance.sina.cn/7x24/2020-12-15/detail-iiznctke6517129.d.html",
            "title": "  特斯拉涨超5%，马斯克内部邮件称要提高产量，2020年总销量目标为50万。",
            "date_modified": "2020-12-14T17:44:35.000Z"
        },
        {
            "id": 1930617,
            "content_html": "",
            "url": "https://finance.sina.cn/7x24/2020-12-15/detail-iiznctke6516040.d.html",
            "title": "土耳其总统埃尔多安宣布12月31日开始全面宵禁，直至1月4日。",
            "date_modified": "2020-12-14T17:23:32.000Z"
        },
        {
            "id": 1930616,
            "content_html": "",
            "url": "https://finance.sina.cn/7x24/2020-12-15/detail-iiznctke6515708.d.html",
            "title": "南非：新增Sarah Baartman和Garden Route这两个地区为新冠肺炎热点地区。",
            "date_modified": "2020-12-14T17:19:02.000Z"
        },
        {
            "id": 1930615,
            "content_html": "",
            "url": "https://finance.sina.cn/7x24/2020-12-15/detail-iiznctke6515705.d.html",
            "title": "  空客CEO：欧盟和英国达成脱欧协议会更好。如果没有脱欧协议，将准备好应对后勤问题，但这将是可控的。",
            "date_modified": "2020-12-14T17:18:56.000Z"
        },
        {
            "id": 1930614,
            "content_html": "",
            "url": "https://finance.sina.cn/7x24/2020-12-15/detail-iiznctke6515547.d.html",
            "title": "  美元兑加元USD/CAD短线走低近20点，现报1.2773。",
            "date_modified": "2020-12-14T17:15:44.000Z"
        },
        {
            "id": 1930613,
            "content_html": "",
            "url": "https://finance.sina.cn/7x24/2020-12-15/detail-iiznctke6515545.d.html",
            "title": "法国最近24小时新增3063例新冠肺炎病例，新增371例死亡病例、累计死亡58282例。",
            "date_modified": "2020-12-14T17:15:36.000Z"
        },
        {
            "id": 1930612,
            "content_html": "",
            "title": "美国白宫新冠肺炎疫苗研发工作组Warp Speed首席运营官（COO）Perna：辉瑞制药发送了145个批次的新冠肺炎疫苗货物，美国（政府）已经接收到其中的55批。已经为周二（12月15日）将会发放的疫苗进行打包和检查。预计将在周三之后追加581个批次的疫苗货物。预计Moderna的新冠肺炎疫苗将于下周投入接种。",
            "date_modified": "2020-12-14T17:15:27.000Z"
        },
        {
            "id": 1930611,
            "content_html": "",
            "url": "https://finance.sina.cn/7x24/2020-12-15/detail-iiznezxs6932267.d.html",
            "title": "美国白宫新冠肺炎疫苗研发工作组Warp Speed首席运营官（COO）Perna：辉瑞制药发送了145个批次的新冠肺炎疫苗货物，美国（政府）已经接收到其中的55批。",
            "date_modified": "2020-12-14T17:12:57.000Z"
        },
        {
            "id": 1930610,
            "content_html": "",
            "url": "https://finance.sina.cn/7x24/2020-12-15/detail-iiznctke6515227.d.html",
            "title": "高盛：航空业的恢复可能会较预期提前。",
            "date_modified": "2020-12-14T17:09:24.000Z"
        },
        {
            "id": 1930609,
            "content_html": "",
            "url": "https://finance.sina.cn/7x24/2020-12-15/detail-iiznctke6515012.d.html",
            "title": "国际铜夜盘收跌0.23%，沪铜收跌0.35%，沪铝收平，沪锌收跌0.14%，沪铅收跌0.50%，沪镍收涨0.63%，沪锡收涨1.68%。",
            "date_modified": "2020-12-14T17:05:41.000Z"
        },
        {
            "id": 1930608,
            "content_html": "",
            "url": "https://finance.sina.cn/7x24/2020-12-15/detail-iiznezxs6931905.d.html",
            "title": "  法国政府文件显示，法国方面要求公共机构和私人机构将现金留在财政部以加强现金流。",
            "date_modified": "2020-12-14T17:05:30.000Z"
        },
        {
            "id": 1930607,
            "content_html": "",
            "url": "https://finance.sina.cn/7x24/2020-12-15/detail-iiznezxs6931607.d.html",
            "title": "  德国副财长Kukies：不断上升的不良贷款不会危及金融市场的稳定。",
            "date_modified": "2020-12-14T17:00:52.000Z"
        },
        {
            "id": 1930606,
            "content_html": "",
            "url": "https://finance.sina.cn/7x24/2020-12-15/detail-iiznctke6514542.d.html",
            "title": "【奥地利首轮大规模检测近尾声，居民参与不足四分之一】当地时间12月14日，奥地利卫生部长安朔贝尔表示，第一轮大规模新冠病毒检测工作接近尾声，该国约200万居民参与检测，其中约4200人新冠病毒抗原检测结果呈阳性。安朔贝尔强调，第一轮检测是良好的开始，是遏制奥地利新冠肺炎疫情的重要环节。据悉，奥地利约有890万居民，而参加第一轮大规模检测人数不足25%，此前奥政府希望参加检测的居民为60%。第二轮大规模检测将从明年1月8日至10日开始，为吸引更多居民参加检测，奥政府正在考虑“激励制度”。（央视）",
            "date_modified": "2020-12-14T16:58:40.000Z"
        },
        {
            "id": 1930605,
            "content_html": "",
            "url": "https://finance.sina.cn/7x24/2020-12-15/detail-iiznezxs6931340.d.html",
            "title": "参加2020年度国家医保目录准入谈判的一位药企人士表示，其公司中成药独家品种降价40%。（每经网）",
            "date_modified": "2020-12-14T16:56:25.000Z"
        },
        {
            "id": 1930604,
            "content_html": "",
            "url": "https://finance.sina.cn/7x24/2020-12-15/detail-iiznctke6514265.d.html",
            "title": "  Peloton Interactive目前上涨超4%，Atlassian上涨3.4%，迈威尔科技上涨2.7%，Okta上涨0.7%，Match Group涨0.48%，美国电力涨0.37%；这几只股票被纳入纳斯达克100指数，将于12月21日美股开市前生效。",
            "date_modified": "2020-12-14T16:53:20.000Z"
        },
        {
            "id": 1930603,
            "content_html": "",
            "url": "https://finance.sina.cn/7x24/2020-12-15/detail-iiznctke6514112.d.html",
            "title": "  美国政府“曲速行动”首席顾问SLAOUI：阿斯利康新冠疫苗的紧急使用授权最早可能在2021年2月提交。",
            "date_modified": "2020-12-14T16:50:54.000Z"
        },
        {
            "id": 1930602,
            "content_html": "",
            "url": "https://finance.sina.cn/7x24/2020-12-15/detail-iiznezxs6930912.d.html",
            "title": "  世卫组织卫生紧急项目负责人瑞安：我们了解到新冠肺炎病毒在英国出现变异，这种进化和突变相当常见。",
            "date_modified": "2020-12-14T16:48:58.000Z"
        },
        {
            "id": 1930601,
            "content_html": "",
            "url": "https://finance.sina.cn/7x24/2020-12-15/detail-iiznctke6513944.d.html",
            "title": "【各地争相布局，加快培育新能源汽车产业】近一个多月来，已有河南、合肥、昆明、广州等地做出规划和部署，包括完善新能源汽车技术创新体系，加快建设基础设施，培育行业领军企业，瞄准千亿市场空间加快培育新能源汽车产业等。（经参）",
            "date_modified": "2020-12-14T16:47:51.000Z"
        },
        {
            "id": 1930600,
            "content_html": "",
            "url": "https://finance.sina.cn/7x24/2020-12-15/detail-iiznctke6513885.d.html",
            "title": "  美国政府“曲速行动”首席顾问SLAOUI：美国政府正在与辉瑞公司积极讨论扩大美国人使用（其新冠疫苗）的剂量。",
            "date_modified": "2020-12-14T16:47:00.000Z"
        },
        {
            "id": 1930599,
            "content_html": "",
            "url": "https://finance.sina.cn/7x24/2020-12-15/detail-iiznctke6513849.d.html",
            "title": "10年期美债收益率日内转跌，并跌至0.9%关口下方，报0.8931%，较日高回落超4个基点。",
            "date_modified": "2020-12-14T16:46:26.000Z"
        },
        {
            "id": 1930598,
            "content_html": "",
            "url": "https://finance.sina.cn/7x24/2020-12-15/detail-iiznezxs6930677.d.html",
            "title": "  欧股收盘涨跌不一，德国DAX指数涨0.82%报13221.34点，法国CAC40指数涨0.37%报5527.84点，英国富时100指数跌0.23%报6531.83点。",
            "date_modified": "2020-12-14T16:44:39.000Z"
        },
        {
            "id": 1930597,
            "content_html": "",
            "url": "https://finance.sina.cn/7x24/2020-12-15/detail-iiznctke6513474.d.html",
            "title": "  美国卫生与公众服务部长亚历克斯·阿扎：美国疾控中心向各州拨款1.4亿美元用于继续规划新冠疫苗的分配工作。",
            "date_modified": "2020-12-14T16:41:03.000Z"
        },
        {
            "id": 1930596,
            "content_html": "",
            "url": "https://finance.sina.cn/7x24/2020-12-15/detail-iiznezxs6930049.d.html",
            "title": "欧洲STOXX 600指数初步收涨0.64%，报392.62点。德国DAX 30指数初步收涨1.05%，报13252.34点。",
            "date_modified": "2020-12-14T16:36:47.000Z"
        },
        {
            "id": 1930595,
            "content_html": "",
            "url": "https://finance.sina.cn/7x24/2020-12-15/detail-iiznctke6512964.d.html",
            "title": "  市场消息：欧佩克+将下一次联合部长级监督委员会和欧佩克技术委员会会议推迟至1月3日和4日举办。",
            "date_modified": "2020-12-14T16:34:43.000Z"
        },
        {
            "id": 1930594,
            "content_html": "",
            "url": "https://finance.sina.cn/7x24/2020-12-15/detail-iiznezxs6929706.d.html",
            "title": "辉瑞制药跌穿40美元，为12月4日以来首次，日内跌幅超过2.7%，经FDA批准，该公司疫苗已经在美国纽约投入接种，这将是美国20世纪50年代小儿麻痹症以来最大规模的免疫努力。",
            "date_modified": "2020-12-14T16:32:24.000Z"
        },
        {
            "id": 1930593,
            "content_html": "",
            "url": "https://finance.sina.cn/7x24/2020-12-15/detail-iiznctke6512649.d.html",
            "title": "  意大利卫生部：截至12月14日，意大利新增12030例新冠肺炎确诊病例和491例死亡病例。",
            "date_modified": "2020-12-14T16:30:11.000Z"
        }
    ]
}